psykickai_tools/__init__.py
psykickai_tools/io/__init__.py
psykickai_tools/io/file_ops.py
psykickai_tools/utils/__init__.py
psykickai_tools/utils/logger.py
psykickai_tools/utils/pydantic_models.py
psykickai_tools/web/__init__.py
psykickai_tools/web/webpage_loader.py
psykickai_tools/web/youtube.py
psykickai_tools-0.2.0.dist-info/LICENSE
psykickai_tools-0.2.0.dist-info/METADATA
psykickai_tools-0.2.0.dist-info/WHEEL
psykickai_tools-0.2.0.dist-info/RECORD
