Metadata-Version: 2.3
Name: psykickai-tools
Version: 0.2.0
Summary: A collection of reusable Python tools and utilities (logging, etc.) designed to streamline project setup and provide out-of-the-box functionality for common development needs.
License: MIT
Keywords: python,tools,utilities,logging
Author: Gaurav Sharma
Author-email: psykickai@gmail.com
Requires-Python: ==3.12.8
Classifier: Development Status :: 3 - Alpha
Classifier: Intended Audience :: Developers
Classifier: License :: OSI Approved :: MIT License
Classifier: Programming Language :: Python :: 3
Classifier: Programming Language :: Python :: 3.12
Requires-Dist: bs4 (>=0.0.2,<0.0.3)
Requires-Dist: lxml (>=5.3.0,<6.0.0)
Requires-Dist: pandas (>=2.2.3,<3.0.0)
Requires-Dist: pydantic (>=2.10.6,<3.0.0)
Requires-Dist: youtube-transcript-api (>=0.6.2,<1.0.0)
Project-URL: Homepage, https://github.com/psykick-21/psykickai-tools
Project-URL: Repository, https://github.com/psykick-21/psykickai-tools
